{
    "PHI": [
        "PHI"
    ],
    "SEA": [
        "SEA"
    ],
    "NYJ": [
        "NYJ"
    ],
    "ARI": [
        "ARI"
    ],
    "CHI": [
        "CHI"
    ],
    "TEN": [
        "TEN"
    ],
    "NYG": [
        "NYG"
    ],
    "LA": [
        "LA",
        "STL"
    ],
    "CAR": [
        "CAR"
    ],
    "CLE": [
        "CLE"
    ],
    "ATL": [
        "ATL"
    ],
    "NE": [
        "NE"
    ],
    "BAL": [
        "BAL"
    ],
    "LV": [
        "LV",
        "OAK"
    ],
    "HOU": [
        "HOU"
    ],
    "IND": [
        "IND"
    ],
    "NO": [
        "NO"
    ],
    "SF": [
        "SF"
    ],
    "DET": [
        "DET"
    ],
    "MIA": [
        "MIA"
    ],
    "DEN": [
        "DEN"
    ],
    "BUF": [
        "BUF"
    ],
    "PIT": [
        "PIT"
    ],
    "DAL": [
        "DAL"
    ],
    "KC": [
        "KC"
    ],
    "LAC": [
        "LAC",
        "SD"
    ],
    "CIN": [
        "CIN"
    ],
    "TB": [
        "TB"
    ],
    "MIN": [
        "MIN"
    ],
    "JAX": [
        "JAX"
    ],
    "GB": [
        "GB"
    ],
    "WAS": [
        "WAS"
    ]
}